django_perms_provisioner/__init__.py
django_perms_provisioner/management/__init__.py
django_perms_provisioner/management/schemas.py
django_perms_provisioner/management/commands/__init__.py
django_perms_provisioner/management/commands/dumpperms.py
django_perms_provisioner/management/commands/loadperms.py
django_perms_provisioner-0.0.6.dist-info/LICENSE
django_perms_provisioner-0.0.6.dist-info/METADATA
django_perms_provisioner-0.0.6.dist-info/WHEEL
django_perms_provisioner-0.0.6.dist-info/top_level.txt
django_perms_provisioner-0.0.6.dist-info/RECORD
