Metadata-Version: 2.1
Name: django-perms-provisioner
Version: 0.0.6
Summary: Provision django instances with usergroups and permissions
Home-page: https://github.com/labd/django-perms-provisioner
Author: Lab Digital
Author-email: opensource@labdigital.nl
License: MIT
Platform: UNKNOWN
Classifier: Development Status :: 5 - Production/Stable
Classifier: Environment :: Web Environment
Classifier: Framework :: Django
Classifier: Framework :: Django :: 1.11
Classifier: Framework :: Django :: 2.0
Classifier: Framework :: Django :: 2.1
Classifier: License :: OSI Approved :: MIT License
Classifier: Programming Language :: Python
Classifier: Programming Language :: Python :: 3
Classifier: Programming Language :: Python :: 3.6
Classifier: Programming Language :: Python :: 3.7
Classifier: Programming Language :: Python :: 3.8
Classifier: Programming Language :: Python :: 3.9
Requires-Dist: Cerberus (<2,>=1.3.2)
Requires-Dist: Django (>=1.11)
Requires-Dist: PyYAML (<7,>=5.3.1)
Provides-Extra: docs
Requires-Dist: sphinx (>=1.4.0) ; extra == 'docs'
Provides-Extra: test
Requires-Dist: coverage ; extra == 'test'
Requires-Dist: pytest (==3.8.1) ; extra == 'test'
Requires-Dist: pytest-cov (==2.6.0) ; extra == 'test'
Requires-Dist: pytest-django (==3.4.3) ; extra == 'test'
Requires-Dist: isort (==4.2.5) ; extra == 'test'
Requires-Dist: flake8 (==3.5.0) ; extra == 'test'
Requires-Dist: flake8-blind-except (==0.1.1) ; extra == 'test'
Requires-Dist: flake8-debugger (==3.1.0) ; extra == 'test'
